odoo/addons/stock_picking_group_by_partner_by_carrier/README.rst
odoo/addons/stock_picking_group_by_partner_by_carrier/__init__.py
odoo/addons/stock_picking_group_by_partner_by_carrier/__manifest__.py
odoo/addons/stock_picking_group_by_partner_by_carrier/i18n/de.po
odoo/addons/stock_picking_group_by_partner_by_carrier/i18n/es.po
odoo/addons/stock_picking_group_by_partner_by_carrier/i18n/fr.po
odoo/addons/stock_picking_group_by_partner_by_carrier/i18n/it.po
odoo/addons/stock_picking_group_by_partner_by_carrier/i18n/pt_BR.po
odoo/addons/stock_picking_group_by_partner_by_carrier/i18n/stock_picking_group_by_partner_by_carrier.pot
odoo/addons/stock_picking_group_by_partner_by_carrier/models/__init__.py
odoo/addons/stock_picking_group_by_partner_by_carrier/models/procurement_group.py
odoo/addons/stock_picking_group_by_partner_by_carrier/models/res_partner.py
odoo/addons/stock_picking_group_by_partner_by_carrier/models/sale_order.py
odoo/addons/stock_picking_group_by_partner_by_carrier/models/sale_order_line.py
odoo/addons/stock_picking_group_by_partner_by_carrier/models/stock_move.py
odoo/addons/stock_picking_group_by_partner_by_carrier/models/stock_picking.py
odoo/addons/stock_picking_group_by_partner_by_carrier/models/stock_picking_type.py
odoo/addons/stock_picking_group_by_partner_by_carrier/models/stock_rule.py
odoo/addons/stock_picking_group_by_partner_by_carrier/models/stock_warehouse.py
odoo/addons/stock_picking_group_by_partner_by_carrier/readme/CONFIGURE.md
odoo/addons/stock_picking_group_by_partner_by_carrier/readme/CONTRIBUTORS.md
odoo/addons/stock_picking_group_by_partner_by_carrier/readme/CREDITS.md
odoo/addons/stock_picking_group_by_partner_by_carrier/readme/DESCRIPTION.md
odoo/addons/stock_picking_group_by_partner_by_carrier/readme/USAGE.md
odoo/addons/stock_picking_group_by_partner_by_carrier/report/__init__.py
odoo/addons/stock_picking_group_by_partner_by_carrier/report/report_delivery_slip.py
odoo_addon_stock_picking_group_by_partner_by_carrier-18.0.1.2.5.dist-info/METADATA
odoo_addon_stock_picking_group_by_partner_by_carrier-18.0.1.2.5.dist-info/WHEEL
odoo_addon_stock_picking_group_by_partner_by_carrier-18.0.1.2.5.dist-info/top_level.txt
odoo_addon_stock_picking_group_by_partner_by_carrier-18.0.1.2.5.dist-info/RECORD
