Metadata-Version: 2.1
Name: odoo-addon-stock_picking_group_by_partner_by_carrier
Version: 18.0.1.2.5
Requires-Python: >=3.10
Requires-Dist: odoo-addon-delivery_procurement_group_carrier==18.0.*
Requires-Dist: odoo-addon-stock_picking_group_by_base==18.0.*
Requires-Dist: odoo-addon-stock_warehouse_out_pull==18.0.*
Requires-Dist: odoo==18.0.*
Summary: Stock Picking: group by partner and carrier
Home-page: https://github.com/OCA/stock-logistics-workflow
License: AGPL-3
Author: Camptocamp, BCIM, Odoo Community Association (OCA)
Author-email: support@odoo-community.org
Classifier: Programming Language :: Python
Classifier: Framework :: Odoo
Classifier: Framework :: Odoo :: 18.0
Classifier: License :: OSI Approved :: GNU Affero General Public License v3
